{
  "patient_records": "Cartelle cliniche",
  "add_patient": "Aggiungi paziente",
  "search_patients": "Cerca pazienti",
  "patient_name": "Nome del paziente",
  "gender": "Genere",
  "age": "Età",
  "bmi": "BMI",
  "status": "Stato",
  "patients": "Pazienti",
  "reports": "Referti",
  "prevention": "Prevenzione",
  "chat": "Chat",
  "language": "Lingua",
  "history": "Storico",
  "profile": "Profilo",
  "demographics": "Dati demografici",
  "anthropometrics": "Antropometria",
  "cardiorespiratory": "Cardiorespiratorio",
  "nutrition": "Nutrizione", 
  "blood_tests": "Esami del sangue",
  "mental_health": "Salute mentale",
  "exercise": "Esercizio",
  "medical_history": "Storia medica",
  "goals": "Obiettivi",
  "full_name": "Nome completo",
  "date_of_birth": "Data di nascita",
  "biological_sex": "Sesso biologico",
  "male": "Maschio",
  "female": "Femmina",
  "other": "Altro",
  "gender_identity": "Identità di genere",
  "non_binary": "Non binario",
  "transgender": "Transgender", 
  "prefer_not_to_say": "Preferisco non dirlo",
  "ethnicity": "Etnia",
  "white": "Bianco",
  "black_african": "Nero/Africano",
  "asian": "Asiatico",
  "hispanic_latino": "Ispanico/Latino",
  "middle_eastern": "Mediorientale",
  "pacific_islander": "Isolano del Pacifico",
  "indigenous": "Indigeno",
  "mixed": "Misto",
  "country_of_residence": "Paese di residenza",
  "occupation": "Occupazione",
  "socioeconomic_indicator": "Indicatore socioeconomico",
  "high_school_or_less": "Diploma di scuola superiore o meno",
  "some_college": "Alcuni studi universitari",
  "bachelors_degree": "Laurea triennale",
  "graduate_degree": "Laurea magistrale",
  "low_income": "Reddito basso",
  "middle_income": "Reddito medio",
  "high_income": "Reddito alto",
  "weight_kg": "Peso (kg)",
  "height_cm": "Altezza (cm)",
  "bmi_auto_calculated": "BMI (Calcolato automaticamente)",
  "waist_circumference_cm": "Circonferenza vita (cm)",
  "hip_circumference_cm": "Circonferenza fianchi (cm)", 
  "waist_hip_ratio_calculated": "Rapporto vita-fianchi (Calcolato)",
  "bioimpedance_metrics": "Metriche di bioimpedenza",
  "body_fat_percentage": "Percentuale di grasso corporeo",
  "muscle_mass_percentage": "Percentuale di massa muscolare",
  "visceral_fat_level": "Livello di grasso viscerale",
  "bone_mass": "Massa ossea",
  "hydration_status": "Stato di idratazione",
  "resting_heart_rate": "Frequenza cardiaca a riposo",
  "blood_pressure_systolic": "Pressione sanguigna (sistolica)",
  "blood_pressure_diastolic": "Pressione sanguigna (diastolica)", 
  "vo2_max": "VO2 Max",
  "oxygen_saturation": "Saturazione di ossigeno",
  "heart_rate_variability": "Variabilità della frequenza cardiaca",
  "meals_per_week_home": "Pasti preparati in casa a settimana",
  "daily_fruits_vegetables": "Porzioni giornaliere di frutta e verdura",
  "weekly_processed_foods": "Porzioni settimanali di cibi trasformati",
  "water_intake_daily": "Assunzione giornaliera di acqua (L)",
  "alcohol_intake_weekly": "Consumo settimanale di alcol (unità)",
  "vitamin_d_level": "Livello di vitamina D (ng/mL)",
  "food_allergies": "Allergie alimentari",
  "food_dislikes": "Intolleranze/Alimenti non graditi",
  "special_diet": "Dieta speciale",
  "none": "Nessuna",
  "vegan": "Vegana",
  "vegetarian": "Vegetariana",
  "pescatarian": "Pescetariana", 
  "keto": "Cheto",
  "paleo": "Paleo",
  "gluten_free": "Senza glutine",
  "dairy_free": "Senza latticini",
  "mediterranean": "Mediterranea",
  "other": "Altro"



}
